mseo_gifconvert_test/__init__.py
mseo_gifconvert_test/convert.py
mseo_gifconvert_test-1.0.1.dist-info/LICENSE
mseo_gifconvert_test-1.0.1.dist-info/METADATA
mseo_gifconvert_test-1.0.1.dist-info/WHEEL
mseo_gifconvert_test-1.0.1.dist-info/top_level.txt
mseo_gifconvert_test-1.0.1.dist-info/RECORD
